machine_plugins/__init__.py
machine_plugins/__meta__.py
machine_plugins/commander/__init__.py
tests/__init__.py
tests/test_commander.py
slack_machine_plugins-0.1.1.dist-info/LICENSE
slack_machine_plugins-0.1.1.dist-info/METADATA
slack_machine_plugins-0.1.1.dist-info/WHEEL
slack_machine_plugins-0.1.1.dist-info/top_level.txt
slack_machine_plugins-0.1.1.dist-info/RECORD
